Counters/tff.v
module tff(t,clk,reset,q);
input t, clk, reset;
output q;
reg q;

always@(posedge clk or posedge reset)
	if(reset)
 		q <= 1'b0;
	else
		q <= q^t;

endmodule

Counters/tff_tb.v
`include "tff.v"

module tff_tb;
reg t, clk, reset;
wire q;

initial
	begin
$dumpfile("tff_tb.vcd");
$dumpvars(0,tff_tb);
end

tff t1(t, clk, reset, q);


initial
begin
reset=1;
clk =0;
t=0;
end

always 
#5  clk =  ! clk; 

always #5  reset = 0;

always #10 t=~t;
/*
initial
begin
#5 reset =1'b0;
d=0;
#5 d = 1'b1;

end
*/

always@(*)
	begin
 		$display("t=%b, clk=%b, reset=%b,q=%b\n", t, clk, reset, q);
	end 

initial

	#100 $finish;
endmodule

Counters/tff_tb.vcd
$date
	Wed Aug 21 10:17:50 2019
$end
$version
	Icarus Verilog
$end
$timescale
	1s
$end
$scope module tff_tb $end
$var wire 1 ! q $end
$var reg 1 " clk $end
$var reg 1 # reset $end
$var reg 1 $ t $end
$scope module t1 $end
$var wire 1 " clk $end
$var wire 1 # reset $end
$var wire 1 $ t $end
$var reg 1 ! q $end
$upscope $end
$upscope $end
$enddefinitions $end
#0
$dumpvars
0$
1#
0"
0!
$end
#5
0#
1"
#10
0"
1$
#15
1!
1"
#20
0"
0$
#25
1"
#30
0"
1$
#35
0!
1"
#40
0"
0$
#45
1"
#50
0"
1$
#55
1!
1"
#60
0"
0$
#65
1"
#70
0"
1$
#75
0!
1"
#80
0"
0$
#85
1"
#90
0"
1$
#95
1!
1"
#100
0"
0$
