Counters/tff.v
module tff(t,clk,reset,q);
input t, clk, reset;
output q;
reg q;

always@(posedge clk or posedge reset)
	if(reset)
 		q <= 1'b0;
	else
		q <= q^t;

endmodule

Counters/upDown.v
`include "tff.v"

module upDown(t,c,clk,reset,q);

input t,c,clk,reset;
output [2:0]q;
wire and0,and1,or0,and2,and3,or1,c1;

assign c1 = ~c;

tff t0(t,clk,reset,q[0]);
	assign and0 = c1 & q[0];
	assign and1 = c & ~q[0];
	assign or0 = and0 | and1;
tff t1(or0,clk,reset,q[1]);
	assign and2 = and0 & q[1];
	assign and3 = and1 & ~q[1];
	assign or1 = and2 | and3;
tff t2(or1,clk,reset,q[2]);

endmodule

Counters/upDown_tb.v
`include "upDown.v"

module top;

reg t,c,clk,reset;
wire [2:0]q;

upDown upDown_tb(t,c,clk,reset,q);

initial begin
	t = 1'b1; c = 1'b0; clk = 0; reset = 1'b1;
end

always #5 reset = 1'b0;
always #5 clk = !clk;

initial begin
	$monitor($time, " t=%d, c=%d, clk=%d, q=%d, q[0]=%d, q[1]=%d, q[2]=%d",t,c,clk,q,q[0],q[1],q[2]);
	$dumpfile("upDown.vcd");
	$dumpvars;
end

initial #100 $finish;

endmodule

Counters/upDown.vcd
$date
	Wed Aug 21 09:40:55 2019
$end
$version
	Icarus Verilog
$end
$timescale
	1s
$end
$scope module top $end
$var wire 3 ! q [2:0] $end
$var reg 1 " c $end
$var reg 1 # clk $end
$var reg 1 $ reset $end
$var reg 1 % t $end
$scope module upDown_tb $end
$var wire 1 & and0 $end
$var wire 1 ' and1 $end
$var wire 1 ( and2 $end
$var wire 1 ) and3 $end
$var wire 1 " c $end
$var wire 1 * c1 $end
$var wire 1 # clk $end
$var wire 1 + or0 $end
$var wire 1 , or1 $end
$var wire 1 $ reset $end
$var wire 1 % t $end
$var wire 3 - q [2:0] $end
$scope module t0 $end
$var wire 1 # clk $end
$var wire 1 $ reset $end
$var wire 1 % t $end
$var reg 1 . q $end
$upscope $end
$scope module t1 $end
$var wire 1 # clk $end
$var wire 1 $ reset $end
$var wire 1 + t $end
$var reg 1 / q $end
$upscope $end
$scope module t2 $end
$var wire 1 # clk $end
$var wire 1 $ reset $end
$var wire 1 , t $end
$var reg 1 0 q $end
$upscope $end
$upscope $end
$upscope $end
$enddefinitions $end
#0
$dumpvars
00
0/
0.
b0 -
0,
0+
1*
0)
0(
0'
0&
1%
1$
0#
0"
b0 !
$end
#5
1+
1&
b1 !
b1 -
1.
1#
0$
#10
0#
#15
0+
0,
0&
0(
0.
b10 !
b10 -
1/
1#
#20
0#
#25
1,
1+
1(
1&
b11 !
b11 -
1.
1#
#30
0#
#35
0+
0,
0&
0(
0.
0/
b100 !
b100 -
10
1#
#40
0#
#45
1+
1&
b101 !
b101 -
1.
1#
#50
0#
#55
0+
0,
0&
0(
0.
b110 !
b110 -
1/
1#
#60
0#
#65
1,
1+
1(
1&
b111 !
b111 -
1.
1#
#70
0#
#75
0+
0,
0&
0(
0.
0/
b0 !
b0 -
00
1#
#80
0#
#85
1+
1&
b1 !
b1 -
1.
1#
#90
0#
#95
0+
0,
0&
0(
0.
b10 !
b10 -
1/
1#
